yaml_designer/__init__.py
yaml_designer/yaml_designer.py
yaml_designer-0.1.3.dist-info/LICENSE
yaml_designer-0.1.3.dist-info/METADATA
yaml_designer-0.1.3.dist-info/WHEEL
yaml_designer-0.1.3.dist-info/top_level.txt
yaml_designer-0.1.3.dist-info/RECORD
