Metadata-Version: 2.1
Name: yaml-designer
Version: 0.1.3
Summary: A plugin that allows users to dynamically create yaml classes and convert into a yaml file when done
Author-email: Babak Michael Engheta <michaelengheta55@gmail.com>
Maintainer-email: Babak Michael Engheta <michaelengheta55@gmail.com>
License: 
Project-URL: Repository, https://github.com/MichaelE55/yaml-designer
Classifier: Programming Language :: Python
Classifier: Programming Language :: Python :: 3.8
Classifier: Programming Language :: Python :: 3.9
Classifier: Programming Language :: Python :: 3.10
Classifier: Programming Language :: Python :: 3.11
Classifier: Programming Language :: Python :: 3.12
Classifier: Programming Language :: Python :: 3 :: Only
Classifier: Programming Language :: Python :: Implementation :: CPython
Classifier: Programming Language :: Python :: Implementation :: PyPy
Classifier: License :: OSI Approved :: BSD License
Requires-Python: >=3.8
License-File: LICENSE
Requires-Dist: pyyaml >=6.0.1
